{
  "index_name": "cef25fe2-9231-4128-8aec-2c948fedd43f",
  "title": "Kisan Call Centre (KCC) - Transcripts of farmers queries & answers",
  "desc": "Kisan Call Centre (KCC) - Transcripts of farmers queries & answers",
  "org_type": "Central",
  "org": [
    "Ministry of Agriculture and Farmers Welfare",
    "Department of Agriculture and Farmers Welfare"
  ],
  "sector": [
    "Agriculture"
  ],
  "source": "data.gov.in",
  "catalog_uuid": "98521455-da95-4abd-9ea3-271d5c854ac8",
  "visualizable": "0",
  "active": "1",
  "created": 1720774013,
  "updated": 1747287279,
  "created_date": "2024-07-12T14:16:53Z",
  "updated_date": "2025-05-15T05:34:39Z",
  "external_ws": 0,
  "external_ws_url": "",
  "target_bucket": {
    "index": "kcc",
    "type": "kcc"
  },
  "field": [
    {
      "name": "StateName",
      "id": "StateName",
      "type": "keyword"
    },
    {
      "name": "DistrictName",
      "id": "DistrictName",
      "type": "keyword"
    },
    {
      "name": "BlockName",
      "id": "BlockName",
      "type": "keyword"
    },
    {
      "name": "Season",
      "id": "Season",
      "type": "keyword"
    },
    {
      "name": "Sector",
      "id": "Sector",
      "type": "keyword"
    },
    {
      "name": "Category",
      "id": "Category",
      "type": "keyword"
    },
    {
      "name": "Crop",
      "id": "Crop",
      "type": "keyword"
    },
    {
      "name": "QueryType",
      "id": "QueryType",
      "type": "keyword"
    },
    {
      "name": "QueryText",
      "id": "QueryText",
      "type": "keyword"
    },
    {
      "name": "KccAns",
      "id": "KccAns",
      "type": "keyword"
    },
    {
      "name": "CreatedOn",
      "id": "CreatedOn",
      "type": "keyword"
    },
    {
      "name": "Year",
      "id": "year",
      "type": "keyword"
    },
    {
      "name": "Month",
      "id": "month",
      "type": "keyword"
    }
  ],
  "field_dependent": [],
  "order": [
    {
      "name": "StateName",
      "id": "StateName"
    }
  ],
  "field_exposed": [
    {
      "name": "State Name",
      "id": "StateName",
      "type": "keyword",
      "mandatory": true
    },
    {
      "name": "Year",
      "id": "year",
      "type": "keyword",
      "mandatory": true
    },
    {
      "name": "Month",
      "id": "month",
      "type": "keyword"
    }
  ],
  "message": "Resource lists",
  "version": "2.2.0",
  "status": "ok",
  "total": 65514,
  "count": 100,
  "limit": "100",
  "offset": "0",
  "records": [
    {
      "StateName": "MAHARASHTRA",
      "DistrictName": "NAGPUR",
      "BlockName": "0   ",
      "Season": "JAYAD",
      "Sector": "9999",
      "Category": "0",
      "Crop": "9999",
      "QueryType": "9999",
      "QueryText": "INFORMATION ABOUT WETHEAR REPORT.",
      "KccAns": "CLOUDY WETHER CONTINIOUS FOR TWO DAYS.",
      "CreatedOn": "2009-03-15T20:37:37",
      "year": 2009,
      "month": 3
    },
    {
      "StateName": "MAHARASHTRA",
      "DistrictName": "OSMANABAD",
      "BlockName": "0   ",
      "Season": "KHARIF",
      "Sector": "HORTICULTURE",
      "Category": "0",
      "Crop": "Citrus",
      "QueryType": "2",
      "QueryText": "CONTROL MEASURES OF FRUIT DROPPING IN CITRUS PLANT.",
      "KccAns": "SPRAYING OF GA3 1gm _+ 10gm urea/10LT water.",
      "CreatedOn": "2009-03-15T20:40:31",
      "year": 2009,
      "month": 3
    },
    {
      "StateName": "RAJASTHAN",
      "DistrictName": "JAIPUR",
      "BlockName": "0   ",
      "Season": "KHARIF",
      "Sector": "HORTICULTURE",
      "Category": "0",
      "Crop": "1280",
      "QueryType": "29",
      "QueryText": "CHILLI VEG. IS EFFECTED BY SUCKINGPLS TELL ITS CONTROL.",
      "KccAns": "SPRAY DIMETHOATE 30 EC @ 2 ML PER LITER WATER.",
      "CreatedOn": "2009-03-15T20:43:32",
      "year": 2009,
      "month": 3
    },
    {
      "StateName": "ODISHA",
      "DistrictName": "KHORDHA",
      "BlockName": "0   ",
      "Season": "KHARIF",
      "Sector": "HORTICULTURE",
      "Category": "0",
      "Crop": "1280",
      "QueryType": "29",
      "QueryText": "APHID PEST OF CHILLI.",
      "KccAns": "SPRAY IMIDACHLOPRID @1ML/4LIT OF WATER.",
      "CreatedOn": "2009-03-15T20:44:42",
      "year": 2009,
      "month": 3
    },
    {
      "StateName": "MAHARASHTRA",
      "DistrictName": "SATARA",
      "BlockName": "0   ",
      "Season": "JAYAD",
      "Sector": "9999",
      "Category": "0",
      "Crop": "9999",
      "QueryType": "9999",
      "QueryText": "MARKET RATE OF SOYABEAN CROP.",
      "KccAns": "RATE- 2100-2250/Q.",
      "CreatedOn": "2009-03-15T20:45:47",
      "year": 2009,
      "month": 3
    },
    {
      "StateName": "KERALA",
      "DistrictName": "THRISSUR",
      "BlockName": "0   ",
      "Season": "JAYAD",
      "Sector": "ANIMAL HUSBANDRY",
      "Category": "0",
      "Crop": "Rabbit",
      "QueryType": "45",
      "QueryText": "rabbit farming",
      "KccAns": "gave the details",
      "CreatedOn": "2009-03-15T20:46:57",
      "year": 2009,
      "month": 3
    },
    {
      "StateName": "MAHARASHTRA",
      "DistrictName": "AMRAVATI",
      "BlockName": "0   ",
      "Season": "KHARIF",
      "Sector": "HORTICULTURE",
      "Category": "0",
      "Crop": "1324",
      "QueryType": "5",
      "QueryText": "Sowing season and Variety of Papaya.",
      "KccAns": "Papaya can be sowen throughout the year in irrigated condition.Va-CO-2,Pusa Delicious.",
      "CreatedOn": "2009-03-15T20:47:52",
      "year": 2009,
      "month": 3
    },
    {
      "StateName": "KERALA",
      "DistrictName": "PALAKKAD",
      "BlockName": "0   ",
      "Season": "JAYAD",
      "Sector": "9999",
      "Category": "0",
      "Crop": "9999",
      "QueryType": "9999",
      "QueryText": "na",
      "KccAns": "na",
      "CreatedOn": "2009-03-15T20:47:54",
      "year": 2009,
      "month": 3
    },
    {
      "StateName": "UTTAR PRADESH",
      "DistrictName": "FARRUKHABAD",
      "BlockName": "0   ",
      "Season": "KHARIF",
      "Sector": "9999",
      "Category": "0",
      "Crop": "9999",
      "QueryType": "9999",
      "QueryText": "MIRCH KI PATTI MUD RAHI HAI",
      "KccAns": "1.5 ML INDOSULPHANE WITH 1 L OF WATER",
      "CreatedOn": "2009-03-15T21:02:45",
      "year": 2009,
      "month": 3
    },
    {
      "StateName": "KERALA",
      "DistrictName": "KOLLAM",
      "BlockName": "0   ",
      "Season": "JAYAD",
      "Sector": "9999",
      "Category": "0",
      "Crop": "9999",
      "QueryType": "9999",
      "QueryText": "azolla cultivation",
      "KccAns": "explained the method",
      "CreatedOn": "2009-03-15T21:04:07",
      "year": 2009,
      "month": 3
    },
    {
      "StateName": "KERALA",
      "DistrictName": "KANNUR",
      "BlockName": "0   ",
      "Season": "JAYAD",
      "Sector": "ANIMAL HUSBANDRY",
      "Category": "0",
      "Crop": "Bovine(Cow,Buffalo)",
      "QueryType": "Disease Management",
      "QueryText": "ectoparasites in cow",
      "KccAns": "advised tikkill",
      "CreatedOn": "2009-03-15T21:07:02",
      "year": 2009,
      "month": 3
    },
    {
      "StateName": "RAJASTHAN",
      "DistrictName": "JHUNJHUNU",
      "BlockName": "0   ",
      "Season": "KHARIF",
      "Sector": "9999",
      "Category": "0",
      "Crop": "9999",
      "QueryType": "9999",
      "QueryText": "PLS TELL ME VARIETIES OF TINDA.",
      "KccAns": "PLS USE ARKA TINDA,BIKANERI GREEN.",
      "CreatedOn": "2009-03-15T21:08:29",
      "year": 2009,
      "month": 3
    },
    {
      "StateName": "KERALA",
      "DistrictName": "TRIVANDRUM",
      "BlockName": "0   ",
      "Season": "JAYAD",
      "Sector": "9999",
      "Category": "0",
      "Crop": "9999",
      "QueryType": "9999",
      "QueryText": "no of kvk",
      "KccAns": "gave the no",
      "CreatedOn": "2009-03-15T21:08:53",
      "year": 2009,
      "month": 3
    },
    {
      "StateName": "KERALA",
      "DistrictName": "KANNUR",
      "BlockName": "0   ",
      "Season": "JAYAD",
      "Sector": "9999",
      "Category": "0",
      "Crop": "9999",
      "QueryType": "9999",
      "QueryText": "na",
      "KccAns": "na",
      "CreatedOn": "2009-03-15T21:14:07",
      "year": 2009,
      "month": 3
    },
    {
      "StateName": "KERALA",
      "DistrictName": "PALAKKAD",
      "BlockName": "0   ",
      "Season": "JAYAD",
      "Sector": "ANIMAL HUSBANDRY",
      "Category": "0",
      "Crop": "Goat",
      "QueryType": "45",
      "QueryText": "goat rearing-breeds,feeding",
      "KccAns": "gave all the details",
      "CreatedOn": "2009-03-15T21:22:06",
      "year": 2009,
      "month": 3
    },
    {
      "StateName": "UTTAR PRADESH",
      "DistrictName": "FAIZABAD",
      "BlockName": "0   ",
      "Season": "RABI",
      "Sector": "9999",
      "Category": "0",
      "Crop": "9999",
      "QueryType": "9999",
      "QueryText": "MARRIGOLD KA SOWING TIME",
      "KccAns": "LAST JUN,JULY",
      "CreatedOn": "2009-03-15T21:25:19",
      "year": 2009,
      "month": 3
    },
    {
      "StateName": "RAJASTHAN",
      "DistrictName": "JAIPUR",
      "BlockName": "0   ",
      "Season": "RABI",
      "Sector": "HORTICULTURE",
      "Category": "0",
      "Crop": "1279",
      "QueryType": "29",
      "QueryText": "BRINJAL VEG. IS EFFECTED BY SUCKING PEST PLS TELL ITS CONTROL.",
      "KccAns": "SPRAY DIMETHOATE 30 EC @ 2 ML PER LITER WATER.",
      "CreatedOn": "2009-03-15T21:31:10",
      "year": 2009,
      "month": 3
    },
    {
      "StateName": "KERALA",
      "DistrictName": "KOTTAYAM",
      "BlockName": "0   ",
      "Season": "JAYAD",
      "Sector": "9999",
      "Category": "0",
      "Crop": "9999",
      "QueryType": "9999",
      "QueryText": "na",
      "KccAns": "na",
      "CreatedOn": "2009-03-15T21:35:49",
      "year": 2009,
      "month": 3
    },
    {
      "StateName": "KERALA",
      "DistrictName": "KANNUR",
      "BlockName": "0   ",
      "Season": "JAYAD",
      "Sector": "9999",
      "Category": "0",
      "Crop": "9999",
      "QueryType": "9999",
      "QueryText": "na",
      "KccAns": "na",
      "CreatedOn": "2009-03-15T21:36:18",
      "year": 2009,
      "month": 3
    },
    {
      "StateName": "UTTARAKHAND",
      "DistrictName": "HARIDWAR",
      "BlockName": "0   ",
      "Season": "KHARIF",
      "Sector": "HORTICULTURE",
      "Category": "0",
      "Crop": "1296",
      "QueryType": "2",
      "QueryText": "POTATO MEIN PEELAPAN",
      "KccAns": "APPLY CARBENDAZIM@2GM./LIT. OF WATER",
      "CreatedOn": "2009-03-15T21:37:35",
      "year": 2009,
      "month": 3
    },
    {
      "StateName": "UTTAR PRADESH",
      "DistrictName": "MUZAFFARNAGAR",
      "BlockName": "0   ",
      "Season": "KHARIF",
      "Sector": "9999",
      "Category": "0",
      "Crop": "9999",
      "QueryType": "9999",
      "QueryText": "insect in bael",
      "KccAns": "spray monocrotophos @ 2ml/lit of water",
      "CreatedOn": "2009-03-15T21:45:12",
      "year": 2009,
      "month": 3
    },
    {
      "StateName": "RAJASTHAN",
      "DistrictName": "DAUSA",
      "BlockName": "0   ",
      "Season": "KHARIF",
      "Sector": "HORTICULTURE",
      "Category": "0",
      "Crop": "Lemon",
      "QueryType": "Fertilizer Use and Availability",
      "QueryText": "FLOWER ARE DROPING IN LEMON PLANT.",
      "KccAns": "PLS USE SPRAY PALENOFIX 1 ML IN 4 LITER WATER.",
      "CreatedOn": "2009-03-15T21:46:15",
      "year": 2009,
      "month": 3
    },
    {
      "StateName": "WEST BENGAL",
      "DistrictName": "9999",
      "BlockName": "0   ",
      "Season": "KHARIF",
      "Sector": "9999",
      "Category": "0",
      "Crop": "9999",
      "QueryType": "9999",
      "QueryText": "BLANK CALL",
      "KccAns": "BLANK CALL",
      "CreatedOn": "2009-03-16T06:12:46",
      "year": 2009,
      "month": 3
    },
    {
      "StateName": "WEST BENGAL",
      "DistrictName": "9999",
      "BlockName": "0   ",
      "Season": "RABI",
      "Sector": "9999",
      "Category": "0",
      "Crop": "9999",
      "QueryType": "9999",
      "QueryText": "BLANK CALL",
      "KccAns": "BLANK CALL",
      "CreatedOn": "2009-03-16T06:15:07",
      "year": 2009,
      "month": 3
    },
    {
      "StateName": "PUNJAB",
      "DistrictName": "KAPURTHALA",
      "BlockName": "0   ",
      "Season": "JAYAD",
      "Sector": "9999",
      "Category": "0",
      "Crop": "9999",
      "QueryType": "9999",
      "QueryText": "INFORMATION REGARDING PAU MELA ?",
      "KccAns": "I TOLD HIM THAT PAU MELA IS ON 19 -20 MARCH",
      "CreatedOn": "2009-03-16T06:15:36",
      "year": 2009,
      "month": 3
    },
    {
      "StateName": "RAJASTHAN",
      "DistrictName": "CHITTAURGARH",
      "BlockName": "0   ",
      "Season": "JAYAD",
      "Sector": "9999",
      "Category": "0",
      "Crop": "9999",
      "QueryType": "9999",
      "QueryText": "BCDGFDGDG",
      "KccAns": "TRTYRTRTJ",
      "CreatedOn": "2009-03-16T06:15:50",
      "year": 2009,
      "month": 3
    },
    {
      "StateName": "PUNJAB",
      "DistrictName": "HOSHIARPUR",
      "BlockName": "0   ",
      "Season": "KHARIF",
      "Sector": "AGRICULTURE",
      "Category": "0",
      "Crop": "Wheat",
      "QueryType": "2",
      "QueryText": "INFORMATION REGARDING HOW TO CONTROL YELLOW RUST IN WHEAT CROP ?",
      "KccAns": "I TOLD THE FARMER SPRAY TO TILT @ 200ML IN 200 LITER OF WATER/ACRE.",
      "CreatedOn": "2009-03-16T06:15:53",
      "year": 2009,
      "month": 3
    },
    {
      "StateName": "PUNJAB",
      "DistrictName": "AMRITSAR",
      "BlockName": "0   ",
      "Season": "KHARIF",
      "Sector": "ANIMAL HUSBANDRY",
      "Category": "0",
      "Crop": "Bovine(Cow,Buffalo)",
      "QueryType": "45",
      "QueryText": "PROBLEM IN DIGESTIVE SYSTEM OF COW ?",
      "KccAns": "CALL ESCALATED",
      "CreatedOn": "2009-03-16T06:17:34",
      "year": 2009,
      "month": 3
    },
    {
      "StateName": "KARNATAKA",
      "DistrictName": "CHIKMAGALUR",
      "BlockName": "0   ",
      "Season": "RABI",
      "Sector": "9999",
      "Category": "0",
      "Crop": "9999",
      "QueryType": "9999",
      "QueryText": "dasf",
      "KccAns": "dsf",
      "CreatedOn": "2009-03-16T06:18:48",
      "year": 2009,
      "month": 3
    },
    {
      "StateName": "RAJASTHAN",
      "DistrictName": "TONK",
      "BlockName": "0   ",
      "Season": "JAYAD",
      "Sector": "9999",
      "Category": "0",
      "Crop": "9999",
      "QueryType": "9999",
      "QueryText": "GIGYUGY",
      "KccAns": "UGIYGUYG",
      "CreatedOn": "2009-03-16T06:20:30",
      "year": 2009,
      "month": 3
    },
    {
      "StateName": "MADHYA PRADESH",
      "DistrictName": "NARSIMPUR",
      "BlockName": "0   ",
      "Season": "KHARIF",
      "Sector": "9999",
      "Category": "0",
      "Crop": "9999",
      "QueryType": "9999",
      "QueryText": "INFORMATION ABOUT HOW TO CONTROL INSECT IN OKRA?",
      "KccAns": "PLZ...... SPRAY HOSTATHION30ML/PUMP IN OKRA.",
      "CreatedOn": "2009-03-16T06:30:19",
      "year": 2009,
      "month": 3
    },
    {
      "StateName": "MADHYA PRADESH",
      "DistrictName": "PANNA",
      "BlockName": "0   ",
      "Season": "KHARIF",
      "Sector": "9999",
      "Category": "0",
      "Crop": "9999",
      "QueryType": "9999",
      "QueryText": "INFORMATION ABOUT SEED RATE IN VIGNA RADIATA?",
      "KccAns": "PLZ.... SOWING USE SEED RATE 12-15Kg/acre RADIATA.",
      "CreatedOn": "2009-03-16T06:30:19",
      "year": 2009,
      "month": 3
    },
    {
      "StateName": "JAMMU AND KASHMIR",
      "DistrictName": "JAMMU",
      "BlockName": "0   ",
      "Season": "RABI",
      "Sector": "9999",
      "Category": "0",
      "Crop": "9999",
      "QueryType": "9999",
      "QueryText": "TEST CALL?",
      "KccAns": "THANKS FOR CALLING.",
      "CreatedOn": "2009-03-16T06:37:09",
      "year": 2009,
      "month": 3
    },
    {
      "StateName": "WEST BENGAL",
      "DistrictName": "9999",
      "BlockName": "0   ",
      "Season": "KHARIF",
      "Sector": "ANIMAL HUSBANDRY",
      "Category": "0",
      "Crop": "Goat",
      "QueryType": "45",
      "QueryText": "INSECT OF GOAT SKIN.",
      "KccAns": "LEVEL-2.",
      "CreatedOn": "2009-03-16T06:46:32",
      "year": 2009,
      "month": 3
    },
    {
      "StateName": "ODISHA",
      "DistrictName": "CUTTACK",
      "BlockName": "0   ",
      "Season": "RABI",
      "Sector": "9999",
      "Category": "0",
      "Crop": "9999",
      "QueryType": "9999",
      "QueryText": "INFORMATION OF POULTRY FARMING.",
      "KccAns": "TO CONTACT BLOCK VETERINARY OFFICER.",
      "CreatedOn": "2009-03-16T06:55:16",
      "year": 2009,
      "month": 3
    },
    {
      "StateName": "RAJASTHAN",
      "DistrictName": "ALWAR",
      "BlockName": "0   ",
      "Season": "KHARIF",
      "Sector": "9999",
      "Category": "0",
      "Crop": "9999",
      "QueryType": "9999",
      "QueryText": "PROBLEM OF ROOT ROT IN TINDA CROP",
      "KccAns": "THE USE--BAVSTION 50WP",
      "CreatedOn": "2009-03-16T07:01:58",
      "year": 2009,
      "month": 3
    },
    {
      "StateName": "PUNJAB",
      "DistrictName": "HOSHIARPUR",
      "BlockName": "0   ",
      "Season": "KHARIF",
      "Sector": "9999",
      "Category": "0",
      "Crop": "9999",
      "QueryType": "9999",
      "QueryText": "CONTROL FOR YELLOW RUST ?",
      "KccAns": "I TOLD HIM TO SPARY TILT @ 200 ML /200L OF WATER / ACRE",
      "CreatedOn": "2009-03-16T07:06:29",
      "year": 2009,
      "month": 3
    },
    {
      "StateName": "MAHARASHTRA",
      "DistrictName": "SOLAPUR",
      "BlockName": "0   ",
      "Season": "JAYAD",
      "Sector": "9999",
      "Category": "0",
      "Crop": "9999",
      "QueryType": "9999",
      "QueryText": "IN4MATION ON APICULTURE",
      "KccAns": "GIVEN DETAIL & REFER TO CONTACT AGRI. OFFICER",
      "CreatedOn": "2009-03-16T07:25:03",
      "year": 2009,
      "month": 3
    },
    {
      "StateName": "RAJASTHAN",
      "DistrictName": "CHITTAURGARH",
      "BlockName": "0   ",
      "Season": "KHARIF",
      "Sector": "HORTICULTURE",
      "Category": "0",
      "Crop": "1324",
      "QueryType": "5",
      "QueryText": "PL. TELL ME ABOUT THE VARITIES OF PAPAYA PLANTS",
      "KccAns": "PUSA--SURYA, PUSA-DELISIS, C.O-2",
      "CreatedOn": "2009-03-16T07:25:39",
      "year": 2009,
      "month": 3
    },
    {
      "StateName": "MAHARASHTRA",
      "DistrictName": "PARBHANI",
      "BlockName": "0   ",
      "Season": "RABI",
      "Sector": "HORTICULTURE",
      "Category": "0",
      "Crop": "1280",
      "QueryType": "29",
      "QueryText": "ATTACT OF JASSID ON CHILLI",
      "KccAns": "SPRAYING OF MONOCROTOPHOS 10 ML IN 10 LIT OF WATER",
      "CreatedOn": "2009-03-16T07:26:02",
      "year": 2009,
      "month": 3
    },
    {
      "StateName": "MAHARASHTRA",
      "DistrictName": "AHMADNAGAR",
      "BlockName": "0   ",
      "Season": "JAYAD",
      "Sector": "HORTICULTURE",
      "Category": "0",
      "Crop": "Ber",
      "QueryType": "29",
      "QueryText": "VARITIES OF CUCUMBER USE IN SUMMER SEASON.",
      "KccAns": "USE HIMANGI,SHITAL,PUNE KHIRA etc. VARITIES OF CUCUMBER USE IN KHARIF SEASON.",
      "CreatedOn": "2009-03-16T07:29:01",
      "year": 2009,
      "month": 3
    },
    {
      "StateName": "MAHARASHTRA",
      "DistrictName": "AHMADNAGAR",
      "BlockName": "0   ",
      "Season": "RABI",
      "Sector": "HORTICULTURE",
      "Category": "0",
      "Crop": "1268",
      "QueryType": "29",
      "QueryText": "FRIUIT SETTING NIN Mango",
      "KccAns": "palnofix spray of 3 ml 10 lit water",
      "CreatedOn": "2009-03-16T07:32:30",
      "year": 2009,
      "month": 3
    },
    {
      "StateName": "MAHARASHTRA",
      "DistrictName": "AHMADNAGAR",
      "BlockName": "0   ",
      "Season": "RABI",
      "Sector": "HORTICULTURE",
      "Category": "0",
      "Crop": "Ber",
      "QueryType": "29",
      "QueryText": "SPACING OF CUCUMBER IN RING METHOD.",
      "KccAns": "SPACING OF CUCUMBER IN RING METHOD IS 1.5MT X 1MT.",
      "CreatedOn": "2009-03-16T07:32:48",
      "year": 2009,
      "month": 3
    },
    {
      "StateName": "MADHYA PRADESH",
      "DistrictName": "CHHINDWARA",
      "BlockName": "0   ",
      "Season": "RABI",
      "Sector": "HORTICULTURE",
      "Category": "0",
      "Crop": "1275",
      "QueryType": "5",
      "QueryText": "INFORMATION ABOUT NAME OF VARITY IN BOTTLE GOURD?",
      "KccAns": "PLZ..SOWN ON VARITY COIMBATUR-1,ARKA BAHAR AND PUSHA SUMMER ETC.",
      "CreatedOn": "2009-03-16T07:40:33",
      "year": 2009,
      "month": 3
    },
    {
      "StateName": "KARNATAKA",
      "DistrictName": "CHIKMAGALUR",
      "BlockName": "0   ",
      "Season": "RABI",
      "Sector": "9999",
      "Category": "0",
      "Crop": "9999",
      "QueryType": "9999",
      "QueryText": "hkj",
      "KccAns": "klj",
      "CreatedOn": "2009-03-16T07:46:28",
      "year": 2009,
      "month": 3
    },
    {
      "StateName": "RAJASTHAN",
      "DistrictName": "JHUNJHUNU",
      "BlockName": "0   ",
      "Season": "JAYAD",
      "Sector": "9999",
      "Category": "0",
      "Crop": "9999",
      "QueryType": "9999",
      "QueryText": "DTRUTRU",
      "KccAns": "HJVGHFG",
      "CreatedOn": "2009-03-16T07:46:41",
      "year": 2009,
      "month": 3
    },
    {
      "StateName": "MAHARASHTRA",
      "DistrictName": "AHMADNAGAR",
      "BlockName": "0   ",
      "Season": "RABI",
      "Sector": "9999",
      "Category": "0",
      "Crop": "9999",
      "QueryType": "9999",
      "QueryText": "MICRONUTRENT IN WATERMILON",
      "KccAns": "SPRAYING OF MICROLA 25 ML IN 140 LIT OF WATER",
      "CreatedOn": "2009-03-16T07:48:07",
      "year": 2009,
      "month": 3
    },
    {
      "StateName": "ODISHA",
      "DistrictName": "PURI",
      "BlockName": "0   ",
      "Season": "RABI",
      "Sector": "9999",
      "Category": "0",
      "Crop": "9999",
      "QueryType": "9999",
      "QueryText": "STEMBORER PEST OF PADDY.",
      "KccAns": "SPRAY MONOCROTOPHOS @2ML/LIT OF WATER.",
      "CreatedOn": "2009-03-16T07:57:29",
      "year": 2009,
      "month": 3
    },
    {
      "StateName": "KERALA",
      "DistrictName": "KOZHIKODE",
      "BlockName": "0   ",
      "Season": "JAYAD",
      "Sector": "HORTICULTURE",
      "Category": "0",
      "Crop": "Grape",
      "QueryType": "29",
      "QueryText": "Pruning of grapes",
      "KccAns": "Gave pruning length,time etc",
      "CreatedOn": "2009-03-16T08:08:01",
      "year": 2009,
      "month": 3
    },
    {
      "StateName": "KARNATAKA",
      "DistrictName": "KOLAR",
      "BlockName": "0   ",
      "Season": "RABI",
      "Sector": "9999",
      "Category": "0",
      "Crop": "9999",
      "QueryType": "9999",
      "QueryText": "rainfall data",
      "KccAns": "given",
      "CreatedOn": "2009-03-16T08:11:49",
      "year": 2009,
      "month": 3
    },
    {
      "StateName": "RAJASTHAN",
      "DistrictName": "NAGAUR",
      "BlockName": "0   ",
      "Season": "RABI",
      "Sector": "AGRICULTURE",
      "Category": "0",
      "Crop": "1576",
      "QueryType": "1",
      "QueryText": "PLS TELL ME SOWING TIME OF FODDER SORGHUM.",
      "KccAns": "SOWING TIME IS MARCH - APRIL.",
      "CreatedOn": "2009-03-16T08:13:37",
      "year": 2009,
      "month": 3
    },
    {
      "StateName": "RAJASTHAN",
      "DistrictName": "JHUNJHUNU",
      "BlockName": "0   ",
      "Season": "JAYAD",
      "Sector": "HORTICULTURE",
      "Category": "0",
      "Crop": "1325",
      "QueryType": "Fertilizer Use and Availability",
      "QueryText": "POMEGRANATE FLOWERS ARE DROPPING PLS TELL ITS CONTROL.",
      "KccAns": "SPRAY PLANOFIX 4 ML PER 15 LITER WATER.",
      "CreatedOn": "2009-03-16T08:18:19",
      "year": 2009,
      "month": 3
    },
    {
      "StateName": "UTTAR PRADESH",
      "DistrictName": "KHERI",
      "BlockName": "0   ",
      "Season": "KHARIF",
      "Sector": "9999",
      "Category": "0",
      "Crop": "9999",
      "QueryType": "9999",
      "QueryText": "DHAAN KI NURSARI SOOKH RAHI HAI",
      "KccAns": "CLORPAERIPHOS @5lit/hac WITH IRRIGATED WATER",
      "CreatedOn": "2009-03-12T12:31:58",
      "year": 2009,
      "month": 3
    },
    {
      "StateName": "JAMMU AND KASHMIR",
      "DistrictName": "JAMMU",
      "BlockName": "0   ",
      "Season": "KHARIF",
      "Sector": "9999",
      "Category": "0",
      "Crop": "9999",
      "QueryType": "9999",
      "QueryText": "INFORMATION REGARDING KISSAN CALL CENTRE ?",
      "KccAns": "ITS IS FARMER HELP LINE WE PROVIDE INFORMATION REGARDING AGRICULTUTRE,HORTICULTURE,VETY. ETC.",
      "CreatedOn": "2009-03-12T12:32:40",
      "year": 2009,
      "month": 3
    },
    {
      "StateName": "UTTAR PRADESH",
      "DistrictName": "JAUNPUR",
      "BlockName": "0   ",
      "Season": "KHARIF",
      "Sector": "HORTICULTURE",
      "Category": "0",
      "Crop": "1324",
      "QueryType": "2",
      "QueryText": "FLOWER DROP IN PAPAYA",
      "KccAns": "APPLY PLANOFIX @ 0.5ML/LIT OF WATER KA SPRAY KAREIN",
      "CreatedOn": "2009-03-12T12:34:49",
      "year": 2009,
      "month": 3
    },
    {
      "StateName": "UTTAR PRADESH",
      "DistrictName": "MUZAFFARNAGAR",
      "BlockName": "0   ",
      "Season": "KHARIF",
      "Sector": "9999",
      "Category": "0",
      "Crop": "9999",
      "QueryType": "9999",
      "QueryText": "SARSON PEELA HO RAHA HAI",
      "KccAns": "MULTIPLUX @2ml/lit OF WATER KA SPRAY",
      "CreatedOn": "2009-03-12T12:38:10",
      "year": 2009,
      "month": 3
    },
    {
      "StateName": "KERALA",
      "DistrictName": "ALAPPUZHA",
      "BlockName": "0   ",
      "Season": "JAYAD",
      "Sector": "9999",
      "Category": "0",
      "Crop": "9999",
      "QueryType": "9999",
      "QueryText": "biogas",
      "KccAns": "explained",
      "CreatedOn": "2009-03-12T12:46:21",
      "year": 2009,
      "month": 3
    },
    {
      "StateName": "TELANGANA",
      "DistrictName": "WARANGAL",
      "BlockName": "0   ",
      "Season": "KHARIF",
      "Sector": "HORTICULTURE",
      "Category": "0",
      "Crop": "1268",
      "QueryType": "2",
      "QueryText": "ASKED ABOUT CONTROL FOR MANGO MALFORMATION",
      "KccAns": "RECOMMENDED TO SPRAY BAVISTIN 1GR/LITRE",
      "CreatedOn": "2009-03-12T12:51:18",
      "year": 2009,
      "month": 3
    },
    {
      "StateName": "HARYANA",
      "DistrictName": "KARNAL",
      "BlockName": "0   ",
      "Season": "KHARIF",
      "Sector": "9999",
      "Category": "0",
      "Crop": "9999",
      "QueryType": "9999",
      "QueryText": "HOW TO CONTROL LALDIS IN MUSK MELON ?",
      "KccAns": "SPRAY TO ENDOSULPHAN @ 200 ML IN 200 LITRES OF WATER / ACRE .",
      "CreatedOn": "2009-03-12T12:52:56",
      "year": 2009,
      "month": 3
    },
    {
      "StateName": "PUNJAB",
      "DistrictName": "MOGA",
      "BlockName": "0   ",
      "Season": "KHARIF",
      "Sector": "HORTICULTURE",
      "Category": "0",
      "Crop": "1282",
      "QueryType": "5",
      "QueryText": "INFORMATION REGARDING VARIETIES OF BHINDI ?",
      "KccAns": "I TOLD THE KISAN USE VARIETIES PUNJAB-7,PUNJAB-8,PUSA SAWANI,PUNJAB PADMINI.",
      "CreatedOn": "2009-03-12T12:57:40",
      "year": 2009,
      "month": 3
    },
    {
      "StateName": "WEST BENGAL",
      "DistrictName": "HOOGHLY",
      "BlockName": "0   ",
      "Season": "RABI",
      "Sector": "HORTICULTURE",
      "Category": "0",
      "Crop": "1279",
      "QueryType": "29",
      "QueryText": "FRUIT BORRER OF BRINJAL.",
      "KccAns": "SPRAY CARBARIL @ 2.5 GM./LIT. OF WATER.",
      "CreatedOn": "2009-03-12T13:00:14",
      "year": 2009,
      "month": 3
    },
    {
      "StateName": "RAJASTHAN",
      "DistrictName": "BARAN",
      "BlockName": "0   ",
      "Season": "JAYAD",
      "Sector": "HORTICULTURE",
      "Category": "0",
      "Crop": "Tomato",
      "QueryType": "2",
      "QueryText": "PROBLEM OF LEAF CRUL IN TOMATO",
      "KccAns": "U CAN SPRAY DIMETHOATE30EC@2 ML PER LITER WATER",
      "CreatedOn": "2009-03-12T13:00:50",
      "year": 2009,
      "month": 3
    },
    {
      "StateName": "UTTAR PRADESH",
      "DistrictName": "BAHRAICH",
      "BlockName": "0   ",
      "Season": "KHARIF",
      "Sector": "HORTICULTURE",
      "Category": "0",
      "Crop": "1282",
      "QueryType": "5",
      "QueryText": "BHINDI KI VARIETY",
      "KccAns": "PANJAB NO-13,CO-1,ARKA ANAMIKA",
      "CreatedOn": "2009-03-12T13:02:03",
      "year": 2009,
      "month": 3
    },
    {
      "StateName": "GUJARAT",
      "DistrictName": "SURENDRANAGAR",
      "BlockName": "0   ",
      "Season": "KHARIF",
      "Sector": "AGRICULTURE",
      "Category": "0",
      "Crop": "1653",
      "QueryType": "Fertilizer Use and Availability",
      "QueryText": "Asak for the fertilizer dose of groundnut",
      "KccAns": "Use of 20-40-00 kg np/hac. of land",
      "CreatedOn": "2009-03-12T13:07:49",
      "year": 2009,
      "month": 3
    },
    {
      "StateName": "UTTAR PRADESH",
      "DistrictName": "ALLAHABAD",
      "BlockName": "0   ",
      "Season": "RABI",
      "Sector": "HORTICULTURE",
      "Category": "0",
      "Crop": "1282",
      "QueryType": "29",
      "QueryText": "bhindi ke patton me keeda laga hai",
      "KccAns": "spray of nuwan @ 1 ml/litre of water",
      "CreatedOn": "2009-03-12T13:11:08",
      "year": 2009,
      "month": 3
    },
    {
      "StateName": "MAHARASHTRA",
      "DistrictName": "PUNE",
      "BlockName": "0   ",
      "Season": "KHARIF",
      "Sector": "HORTICULTURE",
      "Category": "0",
      "Crop": "Tomato",
      "QueryType": "29",
      "QueryText": "ATTACK OF WILT ON TOMATO.",
      "KccAns": "SPRAYING DIATHENE M-45,2.5 GM/LIT.WATER.",
      "CreatedOn": "2009-03-12T13:11:50",
      "year": 2009,
      "month": 3
    },
    {
      "StateName": "KARNATAKA",
      "DistrictName": "GULBARGA",
      "BlockName": "0   ",
      "Season": "JAYAD",
      "Sector": "9999",
      "Category": "0",
      "Crop": "9999",
      "QueryType": "9999",
      "QueryText": "weather report",
      "KccAns": "info given",
      "CreatedOn": "2009-03-12T13:14:48",
      "year": 2009,
      "month": 3
    },
    {
      "StateName": "UTTAR PRADESH",
      "DistrictName": "GONDA",
      "BlockName": "0   ",
      "Season": "KHARIF",
      "Sector": "AGRICULTURE",
      "Category": "0",
      "Crop": "1064",
      "QueryType": "5",
      "QueryText": "MOONG KI VAR.",
      "KccAns": "MALVIYA JOUTY,MEEHA,MOONG JANPRIYA",
      "CreatedOn": "2009-03-12T13:14:53",
      "year": 2009,
      "month": 3
    },
    {
      "StateName": "GUJARAT",
      "DistrictName": "JAMNAGAR",
      "BlockName": "0   ",
      "Season": "RABI",
      "Sector": "AGRICULTURE",
      "Category": "0",
      "Crop": "Oil palm",
      "QueryType": "3",
      "QueryText": "Asking about sucking pest in Sesamum.",
      "KccAns": "Advice to spray Imidacloroprid 5-7ml/pump.",
      "CreatedOn": "2009-03-12T13:20:08",
      "year": 2009,
      "month": 3
    },
    {
      "StateName": "UTTAR PRADESH",
      "DistrictName": "PRATAPGARH",
      "BlockName": "0   ",
      "Season": "KHARIF",
      "Sector": "HORTICULTURE",
      "Category": "0",
      "Crop": "Onion",
      "QueryType": "2",
      "QueryText": "ONION ME LEAVES JAL RAHI HAI",
      "KccAns": "CARBANDAZIM @2gm/lit OF WATER KA SPRAY",
      "CreatedOn": "2009-03-12T13:25:06",
      "year": 2009,
      "month": 3
    },
    {
      "StateName": "UTTARAKHAND",
      "DistrictName": "NAINITAL",
      "BlockName": "0   ",
      "Season": "KHARIF",
      "Sector": "9999",
      "Category": "0",
      "Crop": "9999",
      "QueryType": "9999",
      "QueryText": "mirccha leaf sikur rahi hai",
      "KccAns": "spray of oga ka 2gm/lit water",
      "CreatedOn": "2009-03-12T13:25:08",
      "year": 2009,
      "month": 3
    },
    {
      "StateName": "UTTAR PRADESH",
      "DistrictName": "9999",
      "BlockName": "0   ",
      "Season": "KHARIF",
      "Sector": "AGRICULTURE",
      "Category": "0",
      "Crop": "Wheat",
      "QueryType": "3",
      "QueryText": "WHEAT KI CROP MEIN CHUHE LAGE HAI",
      "KccAns": "GIVE ZINCK FHASFITE @ 15GM WITH OIL AND AATE MEIN MILAKAR RAKCH DE",
      "CreatedOn": "2009-03-12T13:25:18",
      "year": 2009,
      "month": 3
    },
    {
      "StateName": "KARNATAKA",
      "DistrictName": "BANGALORE",
      "BlockName": "0   ",
      "Season": "JAYAD",
      "Sector": "HORTICULTURE",
      "Category": "0",
      "Crop": "Ber",
      "QueryType": "29",
      "QueryText": "contact number of horticulture department lalbhag",
      "KccAns": "info given",
      "CreatedOn": "2009-03-12T13:26:09",
      "year": 2009,
      "month": 3
    },
    {
      "StateName": "HARYANA",
      "DistrictName": "BHIWANI",
      "BlockName": "0   ",
      "Season": "KHARIF",
      "Sector": "9999",
      "Category": "0",
      "Crop": "9999",
      "QueryType": "9999",
      "QueryText": "INFORMATION REGARDING SOWING TIME OF BITTER GOURD?",
      "KccAns": "I TOLD THE KISAN SOWING TIME OF BITTER GOURD:-FEB TO MARCH.",
      "CreatedOn": "2009-03-12T13:26:24",
      "year": 2009,
      "month": 3
    },
    {
      "StateName": "UTTAR PRADESH",
      "DistrictName": "BADAUN",
      "BlockName": "0   ",
      "Season": "KHARIF",
      "Sector": "HORTICULTURE",
      "Category": "0",
      "Crop": "1280",
      "QueryType": "5",
      "QueryText": "CHILLI KI VAR.",
      "KccAns": "AGNI,JWALA,CHANCHAL",
      "CreatedOn": "2009-03-12T13:26:59",
      "year": 2009,
      "month": 3
    },
    {
      "StateName": "JAMMU AND KASHMIR",
      "DistrictName": "JAMMU",
      "BlockName": "0   ",
      "Season": "RABI",
      "Sector": "HORTICULTURE",
      "Category": "0",
      "Crop": "Tomato",
      "QueryType": "29",
      "QueryText": "WHAT IS THE CONTROL OF WHITE FLY IN TOMATO?",
      "KccAns": "SPRAY MALATHION 50 EC @ 2ML / LITRE OF WATER.",
      "CreatedOn": "2009-03-12T13:27:07",
      "year": 2009,
      "month": 3
    },
    {
      "StateName": "UTTAR PRADESH",
      "DistrictName": "JHANSI",
      "BlockName": "0   ",
      "Season": "KHARIF",
      "Sector": "AGRICULTURE",
      "Category": "0",
      "Crop": "1037",
      "QueryType": "3",
      "QueryText": "gram mein insewct laga hai",
      "KccAns": "apply indosulphan @ 1-1.5ml/liyter of water",
      "CreatedOn": "2009-03-12T13:27:08",
      "year": 2009,
      "month": 3
    },
    {
      "StateName": "GUJARAT",
      "DistrictName": "Mehsana",
      "BlockName": "0   ",
      "Season": "KHARIF",
      "Sector": "9999",
      "Category": "0",
      "Crop": "9999",
      "QueryType": "9999",
      "QueryText": "Ask for the sab sidy in micro nutriant..",
      "KccAns": "Contect to taluka development officer,",
      "CreatedOn": "2009-03-12T13:27:14",
      "year": 2009,
      "month": 3
    },
    {
      "StateName": "UTTAR PRADESH",
      "DistrictName": "SANT KABIR NAGAR",
      "BlockName": "0   ",
      "Season": "KHARIF",
      "Sector": "HORTICULTURE",
      "Category": "0",
      "Crop": "1268",
      "QueryType": "29",
      "QueryText": "mango mein insect laga hai",
      "KccAns": "apply indosulphan @ 1-1.5ml/literof water",
      "CreatedOn": "2009-03-12T13:30:42",
      "year": 2009,
      "month": 3
    },
    {
      "StateName": "HARYANA",
      "DistrictName": "HISSAR",
      "BlockName": "0   ",
      "Season": "KHARIF",
      "Sector": "AGRICULTURE",
      "Category": "0",
      "Crop": "Wheat",
      "QueryType": "2",
      "QueryText": "HOW TO CONTROL YELLOW RUST IN WHEAT CROP ?",
      "KccAns": "SPRAY TO DIATHAIN M45 @ 800 GM IN 250 LITRES OF WATER / ACRE .",
      "CreatedOn": "2009-03-12T13:43:13",
      "year": 2009,
      "month": 3
    },
    {
      "StateName": "WEST BENGAL",
      "DistrictName": "9999",
      "BlockName": "0   ",
      "Season": "KHARIF",
      "Sector": "9999",
      "Category": "0",
      "Crop": "9999",
      "QueryType": "9999",
      "QueryText": "BLANK CALL",
      "KccAns": "BLANK CALL",
      "CreatedOn": "2009-03-12T13:45:06",
      "year": 2009,
      "month": 3
    },
    {
      "StateName": "ANDHRA PRADESH",
      "DistrictName": "9999",
      "BlockName": "0   ",
      "Season": "KHARIF",
      "Sector": "9999",
      "Category": "0",
      "Crop": "9999",
      "QueryType": "9999",
      "QueryText": "BLANK CALL",
      "KccAns": "BLANK CALL",
      "CreatedOn": "2009-03-12T13:45:06",
      "year": 2009,
      "month": 3
    },
    {
      "StateName": "DELHI",
      "DistrictName": "West Delhi (Rajouri Garden)",
      "BlockName": "0   ",
      "Season": "JAYAD",
      "Sector": "9999",
      "Category": "0",
      "Crop": "9999",
      "QueryType": "9999",
      "QueryText": "PLS TELL ME DATE OF AG.FAIR IN PARGATI MADAIN",
      "KccAns": "NO DATE CLEAR",
      "CreatedOn": "2009-03-12T13:47:07",
      "year": 2009,
      "month": 3
    },
    {
      "StateName": "KARNATAKA",
      "DistrictName": "SHIMOGA",
      "BlockName": "0   ",
      "Season": "JAYAD",
      "Sector": "9999",
      "Category": "0",
      "Crop": "9999",
      "QueryType": "9999",
      "QueryText": "warm",
      "KccAns": "given",
      "CreatedOn": "2009-03-12T13:52:39",
      "year": 2009,
      "month": 3
    },
    {
      "StateName": "MAHARASHTRA",
      "DistrictName": "SOLAPUR",
      "BlockName": "0   ",
      "Season": "JAYAD",
      "Sector": "9999",
      "Category": "0",
      "Crop": "9999",
      "QueryType": "9999",
      "QueryText": "VARITIES OF RED ROSE USE IN KHARIF SEASON.",
      "KccAns": "USE GLADIATOR,TORO,PAPA MILAND VARITIES OF RED ROSE .",
      "CreatedOn": "2009-03-12T13:54:02",
      "year": 2009,
      "month": 3
    },
    {
      "StateName": "PUNJAB",
      "DistrictName": "LUDHIANA",
      "BlockName": "0   ",
      "Season": "KHARIF",
      "Sector": "AGRICULTURE",
      "Category": "0",
      "Crop": "Wheat",
      "QueryType": "3",
      "QueryText": "INFORMATION REGARDING APHID IN WHEAT CROP?",
      "KccAns": "I TOLD THE KISAN SPRAY ROGOR @150 ML/100 LITER OF WATER/ACRE.",
      "CreatedOn": "2009-03-12T13:54:08",
      "year": 2009,
      "month": 3
    },
    {
      "StateName": "RAJASTHAN",
      "DistrictName": "JALOR",
      "BlockName": "0   ",
      "Season": "JAYAD",
      "Sector": "9999",
      "Category": "0",
      "Crop": "9999",
      "QueryType": "9999",
      "QueryText": "OOO",
      "KccAns": "OOO",
      "CreatedOn": "2009-03-12T13:55:55",
      "year": 2009,
      "month": 3
    },
    {
      "StateName": "DELHI",
      "DistrictName": "EAST DELHI (Preet Vihar)",
      "BlockName": "0   ",
      "Season": "JAYAD",
      "Sector": "9999",
      "Category": "0",
      "Crop": "9999",
      "QueryType": "9999",
      "QueryText": "PLS TELL ME VARITIES OF SUGERCAN",
      "KccAns": "COJ83,64,LAKNEHU-9414",
      "CreatedOn": "2009-03-12T13:57:05",
      "year": 2009,
      "month": 3
    },
    {
      "StateName": "MAHARASHTRA",
      "DistrictName": "AHMADNAGAR",
      "BlockName": "0   ",
      "Season": "KHARIF",
      "Sector": "HORTICULTURE",
      "Category": "0",
      "Crop": "Banana",
      "QueryType": "Fertilizer Use and Availability",
      "QueryText": "FERTILISER DOSE FOR 4 MONTH BANANA.",
      "KccAns": "GIVES 110 GM UREA,250 GM SUPER PHOSPHATE 350 GM MURRATE OF PATASH PER PLANT.",
      "CreatedOn": "2009-03-12T14:00:09",
      "year": 2009,
      "month": 3
    },
    {
      "StateName": "PUNJAB",
      "DistrictName": "HOSHIARPUR",
      "BlockName": "GARHSHANKAR",
      "Season": "KHARIF",
      "Sector": "9999",
      "Category": "0",
      "Crop": "9999",
      "QueryType": "9999",
      "QueryText": "CONTROL FOR YELLOW RUST?",
      "KccAns": "I TOLD HIM TO SPRAY TILT @ 200 ML / 200 L OF WATER/ACRE",
      "CreatedOn": "2009-03-12T14:00:41",
      "year": 2009,
      "month": 3
    },
    {
      "StateName": "PUNJAB",
      "DistrictName": "LUDHIANA",
      "BlockName": "0   ",
      "Season": "JAYAD",
      "Sector": "9999",
      "Category": "0",
      "Crop": "9999",
      "QueryType": "9999",
      "QueryText": "INFORMATION REGARDING RECOMANDED VARIETIES OF PADDY?",
      "KccAns": "I TOLD THE KISAN PAU-201,PR-118,PR-116,PR-111,PR-115.",
      "CreatedOn": "2009-03-12T14:01:39",
      "year": 2009,
      "month": 3
    },
    {
      "StateName": "HARYANA",
      "DistrictName": "FARIDABAD",
      "BlockName": "0   ",
      "Season": "KHARIF",
      "Sector": "9999",
      "Category": "0",
      "Crop": "9999",
      "QueryType": "9999",
      "QueryText": "INFORMATION REGARDING TO THE WEATHER OF MATHURA ?",
      "KccAns": "I TOLD THE KISAN TO THE WEATHER OF MATHURA IS CLEAR, NO CHANCE OF RAIN.",
      "CreatedOn": "2009-03-12T14:09:10",
      "year": 2009,
      "month": 3
    },
    {
      "StateName": "HARYANA",
      "DistrictName": "KURKSHETRA",
      "BlockName": "0   ",
      "Season": "KHARIF",
      "Sector": "AGRICULTURE",
      "Category": "0",
      "Crop": "Wheat",
      "QueryType": "3",
      "QueryText": "CONTROL OF APHID IN WHEAT CROP?",
      "KccAns": "SPRAY OF ENDOSULFAN @ 500 ML IN 200 LITERS OF WATER PER ACRE.",
      "CreatedOn": "2009-03-12T14:12:51",
      "year": 2009,
      "month": 3
    },
    {
      "StateName": "HIMACHAL PRADESH",
      "DistrictName": "BILASPUR",
      "BlockName": "0   ",
      "Season": "KHARIF",
      "Sector": "ANIMAL HUSBANDRY",
      "Category": "0",
      "Crop": "964",
      "QueryType": "45",
      "QueryText": "INFORMATION REGARDING MY BUFFALO LOW MILK WHAT I DO?",
      "KccAns": "I TOLD THE KISAN GIVE HER MINIRAL MIXTURE @40GM AND OSTA CALICIUM @30ML/DAY.",
      "CreatedOn": "2009-03-12T14:12:52",
      "year": 2009,
      "month": 3
    },
    {
      "StateName": "MAHARASHTRA",
      "DistrictName": "SOLAPUR",
      "BlockName": "0   ",
      "Season": "KHARIF",
      "Sector": "HORTICULTURE",
      "Category": "0",
      "Crop": "Watermelon",
      "QueryType": "29",
      "QueryText": "CONTROL MEASURE FOR FRUIT FLY IN WATERMELON",
      "KccAns": "PLZ. SPRAY QUINOLPHOS 25 EC. 20 ML. IN 10 LIT. OF WATER",
      "CreatedOn": "2009-03-12T14:13:37",
      "year": 2009,
      "month": 3
    },
    {
      "StateName": "PUNJAB",
      "DistrictName": "KAPURTHALA",
      "BlockName": "0   ",
      "Season": "JAYAD",
      "Sector": "9999",
      "Category": "0",
      "Crop": "9999",
      "QueryType": "9999",
      "QueryText": "INFORMATION REGARDING RECOMANDED VARIETIES OF PADDY?",
      "KccAns": "I TOLD THE KISAN PAU-201,PR-118,PR-115,PR-111,PR-114.",
      "CreatedOn": "2009-03-12T14:16:31",
      "year": 2009,
      "month": 3
    },
    {
      "StateName": "RAJASTHAN",
      "DistrictName": "KARAULI",
      "BlockName": "0   ",
      "Season": "JAYAD",
      "Sector": "9999",
      "Category": "0",
      "Crop": "9999",
      "QueryType": "9999",
      "QueryText": "OOO",
      "KccAns": "OOO",
      "CreatedOn": "2009-03-12T14:16:43",
      "year": 2009,
      "month": 3
    },
    {
      "StateName": "KARNATAKA",
      "DistrictName": "9999",
      "BlockName": "0   ",
      "Season": "RABI",
      "Sector": "9999",
      "Category": "0",
      "Crop": "9999",
      "QueryType": "9999",
      "QueryText": "kji",
      "KccAns": "uij",
      "CreatedOn": "2009-03-12T14:17:46",
      "year": 2009,
      "month": 3
    },
    {
      "StateName": "KARNATAKA",
      "DistrictName": "CHITRADURGA",
      "BlockName": "0   ",
      "Season": "RABI",
      "Sector": "9999",
      "Category": "0",
      "Crop": "9999",
      "QueryType": "9999",
      "QueryText": "weather report",
      "KccAns": "info given",
      "CreatedOn": "2009-03-12T14:20:42",
      "year": 2009,
      "month": 3
    },
    {
      "StateName": "PUNJAB",
      "DistrictName": "HOSHIARPUR",
      "BlockName": "0   ",
      "Season": "KHARIF",
      "Sector": "ANIMAL HUSBANDRY",
      "Category": "0",
      "Crop": "Bovine(Cow,Buffalo)",
      "QueryType": "45",
      "QueryText": "CONTROL OF TEET PROBLEM IN COW ?",
      "KccAns": "Escalation Level 2",
      "CreatedOn": "2009-03-12T14:28:24",
      "year": 2009,
      "month": 3
    }
  ]
}